django_iran_ip/__init__.py
django_iran_ip/conf.py
django_iran_ip/contrib/__init__.py
django_iran_ip/contrib/django/__init__.py
django_iran_ip/contrib/django/middleware.py
django_iran_ip/contrib/django/utils.py
django_iran_ip/core/__init__.py
django_iran_ip/core/base.py
django_iran_ip/core/resolver.py
django_iran_ip/core/spoofing.py
django_iran_ip/core/strategies.py
django_iran_ip/core/validators.py
django_iran_ip-0.2.0.dist-info/licenses/LICENSE
django_iran_ip-0.2.0.dist-info/METADATA
django_iran_ip-0.2.0.dist-info/WHEEL
django_iran_ip-0.2.0.dist-info/RECORD
