Metadata-Version: 2.4
Name: django-iran-ip
Version: 0.2.0
Summary: A professional Django package for IP detection with Iran network support
License-File: LICENSE
Author: shayan taki
Author-email: takishayan@icloud.com
Requires-Python: >=3.10
Classifier: Programming Language :: Python :: 3
Classifier: Programming Language :: Python :: 3.10
Classifier: Programming Language :: Python :: 3.11
Classifier: Programming Language :: Python :: 3.12
Classifier: Programming Language :: Python :: 3.13
Classifier: Programming Language :: Python :: 3.14
Requires-Dist: django (>=4.2,<6.0)
Requires-Dist: httpx (>=0.28.1,<0.29.0)
